{"type":"Ukagaka Model Setting","name":"chiyo","model":"chiyo.moc","filepath":"/js/ukagaka/assets/chiyo/","playlist":[{"title":"シュガーソングとビターステップ","artist":"血界戰線 ED","album":"","cover":"","mp3":"http://morris821028.github.io/file/music/Kekkai-Sensen-ED-Instrumental-ED.mp3","ogg":"http://morris821028.github.io/file/music/Kekkai-Sensen-ED-Instrumental-ED.mp3"},{"title":"さよならのこと","artist":"WHITE ALBUM2 ED","album":"","cover":"","mp3":"http://morris821028.github.io/file/music/WHITE-ALBUM2-ED-Piano.mp3","ogg":"http://morris821028.github.io/file/music/WHITE-ALBUM2-ED-Piano.mp3"}],"motions":{"idle":[{"file":"motions/uk12.png"},{"file":"motions/uk13.png"},{"file":"motions/uk14.png"},{"file":"motions/uk15.png"},{"file":"motions/uk16.png"},{"file":"motions/uk17.png"},{"file":"motions/uk18.png"},{"file":"motions/uk20.png"},{"file":"motions/uk21.png"},{"file":"motions/uk23.png"},{"file":"motions/uk24.png"},{"file":"motions/uk25.png"},{"file":"motions/uk26.png"},{"file":"motions/uk27.png"}]},"ui":{"ukagakaText":"千代","loadingText":" .^100.^100.","learnPlaceholder":"default: input for learn.","menuMainText":"使用選單功能&#65292; 為什麼要聽你的！","menuLearnText":"$ 學習","menuLogText":"$ 日誌","menuExitText":"$ 結束","menuCancelText":"$ 取消","menuSubmitText":"$ 確認","menuQueryText":"請輸入想要讓千代學的話<br/><br/>","logText":"更新日誌<br/><br/>Morris 修正<br/><br/>找尋 AI 系統<br/>找尋 AI 對話<br/>","rejectText":"千代不接受這個字串喔！","learnText":"千代學習了！"}}